{
  "name": "Israel",
  "slug": "israel",
  "official_name": "Israel",
  "cca2": "",
  "cca3": "",
  "region": "Asia",
  "subregion": "Western Asia",
  "region_slug": "asia",
  "capital": "Jerusalem",
  "population": 9220000,
  "area": 0,
  "currency": "Israeli New Shekel (ILS)",
  "languages": [
    "Hebrew"
  ],
  "language": "Hebrew",
  "timezone": "UTC+2",
  "timezones": [
    "UTC+2"
  ],
  "flag_emoji": "",
  "flag_svg": "",
  "flag_png": "",
  "coat_of_arms": "",
  "maps_google": "",
  "maps_osm": "",
  "landlocked": false,
  "borders": [],
  "driving_side": "right",
  "calling_code": "",
  "safety_level": "caution",
  "budget_per_day": {
    "budget": "90-120",
    "midrange": "160-240",
    "luxury": "420+"
  },
  "best_time_to_visit": "Mar-May, Sep-Nov",
  "latlng": [
    0,
    0
  ],
  "capital_latlng": [
    0,
    0
  ],
  "un_member": true,
  "independent": true,
  "featured": false
}